pepperpy/__init__.py
pepperpy/ai/__init__.py
pepperpy/ai/agents/__init__.py
pepperpy/ai/agents/analysis.py
pepperpy/ai/agents/architect.py
pepperpy/ai/agents/base.py
pepperpy/ai/agents/development.py
pepperpy/ai/agents/factory.py
pepperpy/ai/agents/interfaces.py
pepperpy/ai/agents/management.py
pepperpy/ai/agents/qa.py
pepperpy/ai/agents/research.py
pepperpy/ai/agents/researcher.py
pepperpy/ai/agents/reviewer.py
pepperpy/ai/agents/specialized.py
pepperpy/ai/agents/team.py
pepperpy/ai/agents/team_types.py
pepperpy/ai/agents/types.py
pepperpy/ai/cache.py
pepperpy/ai/chat/__init__.py
pepperpy/ai/chat/conversation.py
pepperpy/ai/chat/types.py
pepperpy/ai/client.py
pepperpy/ai/config.py
pepperpy/ai/embeddings/__init__.py
pepperpy/ai/embeddings/base.py
pepperpy/ai/embeddings/client.py
pepperpy/ai/embeddings/config.py
pepperpy/ai/embeddings/exceptions.py
pepperpy/ai/embeddings/providers/__init__.py
pepperpy/ai/embeddings/providers/base.py
pepperpy/ai/embeddings/providers/sentence_transformers.py
pepperpy/ai/embeddings/types.py
pepperpy/ai/exceptions.py
pepperpy/ai/functions.py
pepperpy/ai/llm/__init__.py
pepperpy/ai/llm/client.py
pepperpy/ai/llm/config.py
pepperpy/ai/llm/exceptions.py
pepperpy/ai/llm/factory.py
pepperpy/ai/llm/types.py
pepperpy/ai/module.py
pepperpy/ai/providers/__init__.py
pepperpy/ai/providers/anthropic.py
pepperpy/ai/providers/base.py
pepperpy/ai/providers/exceptions.py
pepperpy/ai/providers/factory.py
pepperpy/ai/providers/openai.py
pepperpy/ai/providers/openrouter.py
pepperpy/ai/providers/stackspot.py
pepperpy/ai/providers/types.py
pepperpy/ai/teams/__init__.py
pepperpy/ai/teams/autogen/__init__.py
pepperpy/ai/teams/autogen/team.py
pepperpy/ai/teams/crew/__init__.py
pepperpy/ai/teams/crew/team.py
pepperpy/ai/teams/factory.py
pepperpy/ai/teams/interfaces.py
pepperpy/ai/teams/langchain/__init__.py
pepperpy/ai/teams/langchain/team.py
pepperpy/ai/teams/manager.py
pepperpy/ai/teams/providers/__init__.py
pepperpy/ai/teams/providers/autogen.py
pepperpy-1.3.7.dist-info/LICENSE
pepperpy-1.3.7.dist-info/METADATA
pepperpy-1.3.7.dist-info/WHEEL
pepperpy-1.3.7.dist-info/entry_points.txt
pepperpy-1.3.7.dist-info/RECORD
